yaml_presorted/__init__.py
yaml_presorted/sort.py
yaml_presorted-0.1.0.dist-info/METADATA
yaml_presorted-0.1.0.dist-info/WHEEL
yaml_presorted-0.1.0.dist-info/entry_points.txt
yaml_presorted-0.1.0.dist-info/RECORD
