Metadata-Version: 2.1
Name: yaml-presorted
Version: 0.1.0
Summary: 
Author: Bohdan Sukhomlinov
Author-email: shellshock1953@gmail.com
Requires-Python: >=3.10,<4.0
Classifier: Programming Language :: Python :: 3
Classifier: Programming Language :: Python :: 3.10
Classifier: Programming Language :: Python :: 3.11
Requires-Dist: ruamel-yaml (>=0.17.32,<0.18.0)
